{"bars": [{"clef": "alto", "first": 0, "key": "A\u266d", "time": "4/4", "verticals": [{"duration": "4", "notes": ["A\u266d3"]}, {"duration": "4", "notes": ["B3"]}, {"duration": "4", "notes": ["D4"]}, {"duration": "4", "notes": ["E\u266f4"]}]}, {"clef": "treble", "first": 4, "key": "A\u266d", "time": "4/4", "verticals": [{"duration": "4", "notes": ["A\u266d4"]}, {"duration": "4", "notes": ["B4"]}, {"duration": "4", "notes": ["D5"]}, {"duration": "4", "notes": ["E\u266f5"]}]}, {"clef": "treble", "first": 8, "key": "A\u266d", "time": "4/4", "verticals": [{"duration": "4", "notes": ["A\u266d5"]}, {"duration": "4", "notes": ["B5"]}, {"duration": "4", "notes": ["D6"]}, {"duration": "4", "notes": ["E\u266f6"]}]}, {"clef": "treble", "first": 12, "key": "A\u266d", "time": "4/4", "verticals": [{"duration": "4", "notes": ["A\u266d6"]}, {"duration": "4", "notes": ["E\u266f6"]}, {"duration": "4", "notes": ["D6"]}, {"duration": "4", "notes": ["B5"]}]}, {"clef": "treble", "first": 16, "key": "A\u266d", "time": "4/4", "verticals": [{"duration": "4", "notes": ["A\u266d5"]}, {"duration": "4", "notes": ["E\u266f5"]}, {"duration": "4", "notes": ["D5"]}, {"duration": "4", "notes": ["B4"]}]}, {"clef": "alto", "first": 20, "key": "A\u266d", "time": "4/4", "verticals": [{"duration": "4", "notes": ["A\u266d4"]}, {"duration": "4", "notes": ["E\u266f4"]}, {"duration": "4", "notes": ["D4"]}, {"duration": "4", "notes": ["B3"]}]}, {"clef": "alto", "first": 24, "key": "A\u266d", "time": "4/4", "verticals": [{"duration": "4", "notes": ["A\u266d3"]}, {"duration": "4", "notes": ["B\u266f3"]}, {"duration": "4", "notes": ["D\u266f4"]}, {"duration": "4", "notes": ["F\u266f4"]}]}, {"clef": "treble", "first": 28, "key": "A\u266d", "time": "4/4", "verticals": [{"duration": "4", "notes": ["A\u266d4"]}, {"duration": "4", "notes": ["B\u266f4"]}, {"duration": "4", "notes": ["D\u266f5"]}, {"duration": "4", "notes": ["F\u266f5"]}]}, {"clef": "treble", "first": 32, "key": "A\u266d", "time": "4/4", "verticals": [{"duration": "4", "notes": ["A\u266d5"]}, {"duration": "4", "notes": ["B\u266f5"]}, {"duration": "4", "notes": ["D\u266f6"]}, {"duration": "4", "notes": ["F\u266f6"]}]}, {"clef": "treble", "first": 36, "key": "A\u266d", "time": "4/4", "verticals": [{"duration": "4", "notes": ["A\u266d6"]}, {"duration": "4", "notes": ["F\u266f6"]}, {"duration": "4", "notes": ["D\u266f6"]}, {"duration": "4", "notes": ["B\u266f5"]}]}, {"clef": "treble", "first": 40, "key": "A\u266d", "time": "4/4", "verticals": [{"duration": "4", "notes": ["A\u266d5"]}, {"duration": "4", "notes": ["F\u266f5"]}, {"duration": "4", "notes": ["D\u266f5"]}, {"duration": "4", "notes": ["B\u266f4"]}]}, {"clef": "alto", "first": 44, "key": "A\u266d", "time": "4/4", "verticals": [{"duration": "4", "notes": ["A\u266d4"]}, {"duration": "4", "notes": ["F\u266f4"]}, {"duration": "4", "notes": ["D\u266f4"]}, {"duration": "4", "notes": ["B\u266f3"]}]}, {"clef": "alto", "first": 48, "key": "A\u266d", "time": "4/4", "verticals": [{"duration": "4", "notes": ["A\u266d3"]}, {"duration": "4r", "notes": ["A\u266d3"]}, {"duration": "4r", "notes": ["A\u266d3"]}, {"duration": "4r", "notes": ["A\u266d3"]}]}], "descriptions": {"en": "A\u266d Major Arpeggio Series \t\u2161 in 3 Octaves", "zh-cn": "A\u266d\u5927\u8c03\u4e09\u4e2a\u516b\u5ea6\u7684\u548c\u5f26\u5e8f\u5217\t\u2161"}, "id": "9cf17e01071c4b97b5f054e9561509e8", "keywords": {"en": "Scale,A\u266d,Arpeggio Series II /3"}}