{"bars": [{"clef": "bass", "first": 0, "key": "e", "time": "3/4", "verticals": [{"duration": "4", "notes": ["E2"]}, {"duration": "4", "notes": ["G2"]}, {"duration": "4", "notes": ["B2"]}]}, {"clef": "bass", "first": 3, "key": "e", "time": "3/4", "verticals": [{"duration": "4", "notes": ["E3"]}, {"duration": "4", "notes": ["B2"]}, {"duration": "4", "notes": ["G2"]}]}, {"clef": "bass", "first": 6, "key": "e", "time": "3/4", "verticals": [{"duration": "4", "notes": ["E2"]}, {"duration": "4r", "notes": ["E2"]}, {"duration": "4r", "notes": ["E2"]}]}], "descriptions": {"en": "e Minor Arpeggio in 1 Octave", "zh-cn": "e\u5c0f\u8c03\u4e00\u4e2a\u516b\u5ea6\u7684\u4e09\u548c\u5f26"}, "id": "047f91a103284e81a0bc0a35f30e8a30", "keywords": {"en": "Scale,e,Arpeggio /1"}}