{"bars": [{"clef": "bass", "first": 0, "key": "g\u266f", "time": "4/4", "verticals": [{"duration": "4", "notes": ["D\u266f2"]}, {"duration": "4", "notes": ["F\ud834\udd2a2"]}, {"duration": "4", "notes": ["A\u266f2"]}, {"duration": "4", "notes": ["C\u266f3"]}]}, {"clef": "bass", "first": 4, "key": "g\u266f", "time": "4/4", "verticals": [{"duration": "4", "notes": ["D\u266f3"]}, {"duration": "4", "notes": ["F\ud834\udd2a3"]}, {"duration": "4", "notes": ["A\u266f3"]}, {"duration": "4", "notes": ["C\u266f4"]}]}, {"clef": "treble", "first": 8, "key": "g\u266f", "time": "4/4", "verticals": [{"duration": "4", "notes": ["D\u266f4"]}, {"duration": "4", "notes": ["C\u266f4"]}, {"duration": "4", "notes": ["A\u266f3"]}, {"duration": "4", "notes": ["F\ud834\udd2a3"]}]}, {"clef": "bass", "first": 12, "key": "g\u266f", "time": "4/4", "verticals": [{"duration": "4", "notes": ["D\u266f3"]}, {"duration": "4", "notes": ["C\u266f3"]}, {"duration": "4", "notes": ["A\u266f2"]}, {"duration": "4", "notes": ["F\ud834\udd2a2"]}]}, {"clef": "bass", "first": 16, "key": "g\u266f", "time": "4/4", "verticals": [{"duration": "4", "notes": ["D\u266f2"]}, {"duration": "4r", "notes": ["D\u266f2"]}, {"duration": "4r", "notes": ["D\u266f2"]}, {"duration": "4r", "notes": ["D\u266f2"]}]}], "descriptions": {"en": "g\u266f Minor Dominant 7th in 2 Octaves", "zh-cn": "g\u266f\u5c0f\u8c03\u4e8c\u4e2a\u516b\u5ea6\u7684\u5927\u4e03\u548c\u5f26"}, "id": "0c3f6927577f46c688583b5c4e5cb6bb", "keywords": {"en": "Scale,g\u266f,Dominant 7th /2"}}