{"bars": [{"clef": "treble", "first": 0, "key": "d", "time": "4/4", "verticals": [{"duration": "4", "notes": ["F4", "D5"]}, {"duration": "4", "notes": ["G4", "E5"]}, {"duration": "4", "notes": ["A4", "F5"]}, {"duration": "4", "notes": ["B\u266d4", "G5"]}]}, {"clef": "treble", "first": 4, "key": "d", "time": "4/4", "verticals": [{"duration": "4", "notes": ["C\u266f5", "A5"]}, {"duration": "4", "notes": ["D5", "B\u266d5"]}, {"duration": "4", "notes": ["E5", "C\u266f6"]}, {"duration": "4", "notes": ["F5", "D6"]}]}, {"clef": "treble", "first": 8, "key": "d", "time": "4/4", "verticals": [{"duration": "4", "notes": ["E5", "C\u266f6"]}, {"duration": "4", "notes": ["D5", "B\u266d5"]}, {"duration": "4", "notes": ["C\u266f5", "A5"]}, {"duration": "4", "notes": ["B\u266d4", "G5"]}]}, {"clef": "treble", "first": 12, "key": "d", "time": "4/4", "verticals": [{"duration": "4", "notes": ["A4", "F5"]}, {"duration": "4", "notes": ["G4", "E5"]}, {"duration": "4", "notes": ["F4", "D5"]}, {"duration": "4r", "notes": ["A4"]}]}], "descriptions": {"en": "d Minor Harmonic Double Stop Sixths Scale in 1 Octave", "zh-cn": "d\u5c0f\u8c03\u4e00\u4e2a\u516b\u5ea6\u7684Harmonic\u53cc\u5f26\u516d\u5ea6\u97f3\u9636"}, "id": "929e65bb804145bf9f310a76cfa75036", "keywords": {"en": "Scale,d,Harmonic Sixths /1"}}