{"bars": [{"clef": "bass", "first": 0, "key": "A\u266d", "time": "3/4", "verticals": [{"duration": "4", "notes": ["A\u266d2"]}, {"duration": "4", "notes": ["C\u266d3"]}, {"duration": "4", "notes": ["E\u266d3"]}]}, {"clef": "treble", "first": 3, "key": "A\u266d", "time": "3/4", "verticals": [{"duration": "4", "notes": ["A\u266d3"]}, {"duration": "4", "notes": ["C\u266d4"]}, {"duration": "4", "notes": ["E\u266d4"]}]}, {"clef": "tenor", "first": 6, "key": "A\u266d", "time": "3/4", "verticals": [{"duration": "4", "notes": ["A\u266d4"]}, {"duration": "4", "notes": ["C\u266d5"]}, {"duration": "4", "notes": ["E\u266d5"]}]}, {"clef": "treble", "first": 9, "key": "A\u266d", "time": "3/4", "verticals": [{"duration": "4", "notes": ["A\u266d5"]}, {"duration": "4", "notes": ["C\u266d6"]}, {"duration": "4", "notes": ["E\u266d6"]}]}, {"clef": "treble", "first": 12, "key": "A\u266d", "time": "3/4", "verticals": [{"duration": "4", "notes": ["A\u266d6"]}, {"duration": "4", "notes": ["E\u266d6"]}, {"duration": "4", "notes": ["C\u266d6"]}]}, {"clef": "tenor", "first": 15, "key": "A\u266d", "time": "3/4", "verticals": [{"duration": "4", "notes": ["A\u266d5"]}, {"duration": "4", "notes": ["E\u266d5"]}, {"duration": "4", "notes": ["C\u266d5"]}]}, {"clef": "tenor", "first": 18, "key": "A\u266d", "time": "3/4", "verticals": [{"duration": "4", "notes": ["A\u266d4"]}, {"duration": "4", "notes": ["E\u266d4"]}, {"duration": "4", "notes": ["C\u266d4"]}]}, {"clef": "bass", "first": 21, "key": "A\u266d", "time": "3/4", "verticals": [{"duration": "4", "notes": ["A\u266d3"]}, {"duration": "4", "notes": ["E\u266d3"]}, {"duration": "4", "notes": ["C\u266d3"]}]}, {"clef": "bass", "first": 24, "key": "A\u266d", "time": "3/4", "verticals": [{"duration": "4", "notes": ["A\u266d2"]}, {"duration": "4", "notes": ["C3"]}, {"duration": "4", "notes": ["E\u266d3"]}]}, {"clef": "treble", "first": 27, "key": "A\u266d", "time": "3/4", "verticals": [{"duration": "4", "notes": ["A\u266d3"]}, {"duration": "4", "notes": ["C4"]}, {"duration": "4", "notes": ["E\u266d4"]}]}, {"clef": "tenor", "first": 30, "key": "A\u266d", "time": "3/4", "verticals": [{"duration": "4", "notes": ["A\u266d4"]}, {"duration": "4", "notes": ["C5"]}, {"duration": "4", "notes": ["E\u266d5"]}]}, {"clef": "treble", "first": 33, "key": "A\u266d", "time": "3/4", "verticals": [{"duration": "4", "notes": ["A\u266d5"]}, {"duration": "4", "notes": ["C6"]}, {"duration": "4", "notes": ["E\u266d6"]}]}, {"clef": "treble", "first": 36, "key": "A\u266d", "time": "3/4", "verticals": [{"duration": "4", "notes": ["A\u266d6"]}, {"duration": "4", "notes": ["E\u266d6"]}, {"duration": "4", "notes": ["C6"]}]}, {"clef": "tenor", "first": 39, "key": "A\u266d", "time": "3/4", "verticals": [{"duration": "4", "notes": ["A\u266d5"]}, {"duration": "4", "notes": ["E\u266d5"]}, {"duration": "4", "notes": ["C5"]}]}, {"clef": "tenor", "first": 42, "key": "A\u266d", "time": "3/4", "verticals": [{"duration": "4", "notes": ["A\u266d4"]}, {"duration": "4", "notes": ["E\u266d4"]}, {"duration": "4", "notes": ["C4"]}]}, {"clef": "bass", "first": 45, "key": "A\u266d", "time": "3/4", "verticals": [{"duration": "4", "notes": ["A\u266d3"]}, {"duration": "4", "notes": ["E\u266d3"]}, {"duration": "4", "notes": ["C3"]}]}, {"clef": "bass", "first": 48, "key": "A\u266d", "time": "3/4", "verticals": [{"duration": "4", "notes": ["A\u266d2"]}, {"duration": "4", "notes": ["C3"]}, {"duration": "4", "notes": ["E\u266f3"]}]}, {"clef": "treble", "first": 51, "key": "A\u266d", "time": "3/4", "verticals": [{"duration": "4", "notes": ["A\u266d3"]}, {"duration": "4", "notes": ["C4"]}, {"duration": "4", "notes": ["E\u266f4"]}]}, {"clef": "tenor", "first": 54, "key": "A\u266d", "time": "3/4", "verticals": [{"duration": "4", "notes": ["A\u266d4"]}, {"duration": "4", "notes": ["C5"]}, {"duration": "4", "notes": ["E\u266f5"]}]}, {"clef": "treble", "first": 57, "key": "A\u266d", "time": "3/4", "verticals": [{"duration": "4", "notes": ["A\u266d5"]}, {"duration": "4", "notes": ["C6"]}, {"duration": "4", "notes": ["E\u266f6"]}]}, {"clef": "treble", "first": 60, "key": "A\u266d", "time": "3/4", "verticals": [{"duration": "4", "notes": ["A\u266d6"]}, {"duration": "4", "notes": ["E\u266f6"]}, {"duration": "4", "notes": ["C6"]}]}, {"clef": "tenor", "first": 63, "key": "A\u266d", "time": "3/4", "verticals": [{"duration": "4", "notes": ["A\u266d5"]}, {"duration": "4", "notes": ["E\u266f5"]}, {"duration": "4", "notes": ["C5"]}]}, {"clef": "tenor", "first": 66, "key": "A\u266d", "time": "3/4", "verticals": [{"duration": "4", "notes": ["A\u266d4"]}, {"duration": "4", "notes": ["E\u266f4"]}, {"duration": "4", "notes": ["C4"]}]}, {"clef": "bass", "first": 69, "key": "A\u266d", "time": "3/4", "verticals": [{"duration": "4", "notes": ["A\u266d3"]}, {"duration": "4", "notes": ["E\u266f3"]}, {"duration": "4", "notes": ["C3"]}]}, {"clef": "bass", "first": 72, "key": "A\u266d", "time": "3/4", "verticals": [{"duration": "4", "notes": ["A\u266d2"]}, {"duration": "4", "notes": ["C\u266f3"]}, {"duration": "4", "notes": ["E\u266f3"]}]}, {"clef": "treble", "first": 75, "key": "A\u266d", "time": "3/4", "verticals": [{"duration": "4", "notes": ["A\u266d3"]}, {"duration": "4", "notes": ["C\u266f4"]}, {"duration": "4", "notes": ["E\u266f4"]}]}, {"clef": "tenor", "first": 78, "key": "A\u266d", "time": "3/4", "verticals": [{"duration": "4", "notes": ["A\u266d4"]}, {"duration": "4", "notes": ["C\u266f5"]}, {"duration": "4", "notes": ["E\u266f5"]}]}, {"clef": "treble", "first": 81, "key": "A\u266d", "time": "3/4", "verticals": [{"duration": "4", "notes": ["A\u266d5"]}, {"duration": "4", "notes": ["C\u266f6"]}, {"duration": "4", "notes": ["E\u266f6"]}]}, {"clef": "treble", "first": 84, "key": "A\u266d", "time": "3/4", "verticals": [{"duration": "4", "notes": ["A\u266d6"]}, {"duration": "4", "notes": ["E\u266f6"]}, {"duration": "4", "notes": ["C\u266f6"]}]}, {"clef": "tenor", "first": 87, "key": "A\u266d", "time": "3/4", "verticals": [{"duration": "4", "notes": ["A\u266d5"]}, {"duration": "4", "notes": ["E\u266f5"]}, {"duration": "4", "notes": ["C\u266f5"]}]}, {"clef": "tenor", "first": 90, "key": "A\u266d", "time": "3/4", "verticals": [{"duration": "4", "notes": ["A\u266d4"]}, {"duration": "4", "notes": ["E\u266f4"]}, {"duration": "4", "notes": ["C\u266f4"]}]}, {"clef": "bass", "first": 93, "key": "A\u266d", "time": "3/4", "verticals": [{"duration": "4", "notes": ["A\u266d3"]}, {"duration": "4", "notes": ["E\u266f3"]}, {"duration": "4", "notes": ["C\u266f3"]}]}, {"clef": "bass", "first": 96, "key": "A\u266d", "time": "3/4", "verticals": [{"duration": "4", "notes": ["A\u266d2"]}, {"duration": "4", "notes": ["C\u266f3"]}, {"duration": "4", "notes": ["E3"]}]}, {"clef": "treble", "first": 99, "key": "A\u266d", "time": "3/4", "verticals": [{"duration": "4", "notes": ["A\u266d3"]}, {"duration": "4", "notes": ["C\u266f4"]}, {"duration": "4", "notes": ["E4"]}]}, {"clef": "tenor", "first": 102, "key": "A\u266d", "time": "3/4", "verticals": [{"duration": "4", "notes": ["A\u266d4"]}, {"duration": "4", "notes": ["C\u266f5"]}, {"duration": "4", "notes": ["E5"]}]}, {"clef": "treble", "first": 105, "key": "A\u266d", "time": "3/4", "verticals": [{"duration": "4", "notes": ["A\u266d5"]}, {"duration": "4", "notes": ["C\u266f6"]}, {"duration": "4", "notes": ["E6"]}]}, {"clef": "treble", "first": 108, "key": "A\u266d", "time": "3/4", "verticals": [{"duration": "4", "notes": ["A\u266d6"]}, {"duration": "4", "notes": ["E6"]}, {"duration": "4", "notes": ["C\u266f6"]}]}, {"clef": "tenor", "first": 111, "key": "A\u266d", "time": "3/4", "verticals": [{"duration": "4", "notes": ["A\u266d5"]}, {"duration": "4", "notes": ["E5"]}, {"duration": "4", "notes": ["C\u266f5"]}]}, {"clef": "tenor", "first": 114, "key": "A\u266d", "time": "3/4", "verticals": [{"duration": "4", "notes": ["A\u266d4"]}, {"duration": "4", "notes": ["E4"]}, {"duration": "4", "notes": ["C\u266f4"]}]}, {"clef": "bass", "first": 117, "key": "A\u266d", "time": "3/4", "verticals": [{"duration": "4", "notes": ["A\u266d3"]}, {"duration": "4", "notes": ["E3"]}, {"duration": "4", "notes": ["C\u266f3"]}]}, {"clef": "bass", "first": 120, "key": "A\u266d", "time": "3/4", "verticals": [{"duration": "4", "notes": ["A\u266d2"]}, {"duration": "4r", "notes": ["A\u266d2"]}, {"duration": "4r", "notes": ["A\u266d2"]}]}], "descriptions": {"en": "A\u266d Major Arpeggio Series \t\u2160 in 4 Octaves", "zh-cn": "A\u266d\u5927\u8c03\u56db\u4e2a\u516b\u5ea6\u7684\u548c\u5f26\u5e8f\u5217\t\u2160"}, "id": "174531d9bc884218a64784180db0d42a", "keywords": {"en": "Scale,A\u266d,Arpeggio Series I /4"}}