{"bars": [{"clef": "bass", "first": 0, "key": "g\u266f", "time": "3/4", "verticals": [{"duration": "4", "notes": ["G\u266f2"]}, {"duration": "4", "notes": ["B2"]}, {"duration": "4", "notes": ["D\u266f3"]}]}, {"clef": "treble", "first": 3, "key": "g\u266f", "time": "3/4", "verticals": [{"duration": "4", "notes": ["G\u266f3"]}, {"duration": "4", "notes": ["B3"]}, {"duration": "4", "notes": ["D\u266f4"]}]}, {"clef": "tenor", "first": 6, "key": "g\u266f", "time": "3/4", "verticals": [{"duration": "4", "notes": ["G\u266f4"]}, {"duration": "4", "notes": ["D\u266f4"]}, {"duration": "4", "notes": ["B3"]}]}, {"clef": "bass", "first": 9, "key": "g\u266f", "time": "3/4", "verticals": [{"duration": "4", "notes": ["G\u266f3"]}, {"duration": "4", "notes": ["D\u266f3"]}, {"duration": "4", "notes": ["B2"]}]}, {"clef": "bass", "first": 12, "key": "g\u266f", "time": "3/4", "verticals": [{"duration": "4", "notes": ["G\u266f2"]}, {"duration": "4r", "notes": ["G\u266f2"]}, {"duration": "4r", "notes": ["G\u266f2"]}]}], "descriptions": {"en": "g\u266f Minor Arpeggio Scale in 2 Octaves", "zh-cn": "g\u266f\u5c0f\u8c03\u4e8c\u4e2a\u516b\u5ea6\u7684\u7436\u97f3\u97f3\u9636"}, "id": "1c6648ba6ca5454d82b469b94c2d0c71", "keywords": {"en": "Scale,g\u266f,Arpeggio /2"}}