{"bars": [{"clef": "bass", "first": 0, "key": "e", "time": "4/4", "verticals": [{"duration": "4", "notes": ["B2"]}, {"duration": "4", "notes": ["D\u266f3"]}, {"duration": "4", "notes": ["F\u266f3"]}, {"duration": "4", "notes": ["A3"]}]}, {"clef": "bass", "first": 4, "key": "e", "time": "4/4", "verticals": [{"duration": "4", "notes": ["B3"]}, {"duration": "4", "notes": ["A3"]}, {"duration": "4", "notes": ["F\u266f3"]}, {"duration": "4", "notes": ["D\u266f3"]}]}, {"clef": "bass", "first": 8, "key": "e", "time": "4/4", "verticals": [{"duration": "4", "notes": ["B2"]}, {"duration": "4r", "notes": ["B2"]}, {"duration": "4r", "notes": ["B2"]}, {"duration": "4r", "notes": ["B2"]}]}], "descriptions": {"en": "e Minor Dominant 7th Scale in 1 Octave", "zh-cn": "e\u5c0f\u8c03\u4e00\u4e2a\u516b\u5ea6\u7684Dominant 7th\u97f3\u9636"}, "id": "863677d675e84ce4b3252f05310f45aa", "keywords": {"en": "Scale,e,Dominant 7th /1"}}